CHANGES.rst
LICENSE
MANIFEST.in
README.md
setup.py
regseg/__about__.py
regseg/__init__.py
regseg/filters.py
regseg/misc.py
regseg/viz.py
regseg.egg-info/PKG-INFO
regseg.egg-info/SOURCES.txt
regseg.egg-info/dependency_links.txt
regseg.egg-info/entry_points.txt
regseg.egg-info/not-zip-safe
regseg.egg-info/requires.txt
regseg.egg-info/top_level.txt
regseg/data/__init__.py
regseg/data/model_labels.json
regseg/data/regseg_default.json
regseg/data/regseg_hcp.json
regseg/data/t2b_elastix_x.txt
regseg/data/t2b_elastix_y.txt
regseg/data/t2b_elastix_z.txt
regseg/interfaces/__init__.py
regseg/interfaces/dmri.py
regseg/interfaces/phantoms.py
regseg/interfaces/regseg.py
regseg/interfaces/utility.py
regseg/interfaces/warps.py
regseg/workflows/__init__.py
regseg/workflows/dti.py
regseg/workflows/evaluation.py
regseg/workflows/fieldmap.py
regseg/workflows/model.py
regseg/workflows/preprocess.py
regseg/workflows/realdata.py
regseg/workflows/registration.py
regseg/workflows/surfaces.py
tools/extract_hcp.py
tools/run_evaluations.py
tools/run_phantoms.py