Metadata-Version: 1.1
Name: regseg
Version: 0.1.1
Summary: Python interface to RegSeg, a surface-driven registration method for the structure-informed segmentation of multispectral brain images
Home-page: http://pyregseg.readthedocs.org/
Author: Oscar Esteban
Author-email: code@oscaresteban.es
License: MIT License
Download-URL: https://github.com/oesteban/pyregseg/archive/0.1.1.tar.gz
Platform: UNKNOWN
Classifier: Development Status :: 3 - Alpha
Classifier: Intended Audience :: Science/Research
Classifier: Topic :: Scientific/Engineering :: Image Recognition
Classifier: License :: OSI Approved :: MIT License
Classifier: Programming Language :: Python :: 2.7
Classifier: Programming Language :: Python :: 3.5
Classifier: Programming Language :: Python :: 3.6
